[
  {
    "id": "m1_sum_basic",
    "category": "word_sum",
    "task": "У Маши 3 яблока, у Пети 5 яблок. Сколько всего яблок?",
    "expected": "8",
    "source": "Math1 p.6-9"
  },
  {
    "id": "m1_remainder_basic",
    "category": "word_remainder",
    "task": "У Пети было 10 машинок, 3 он отдал другу. Сколько осталось?",
    "expected": "7",
    "source": "Math1 p.16-19"
  },
  {
    "id": "m1_compare_difference",
    "category": "word_difference_compare",
    "task": "У Коли 9 наклеек, у Димы 5. На сколько у Коли больше?",
    "expected": "4",
    "source": "Math1 p.20-22"
  },
  {
    "id": "m1_compare_ratio",
    "category": "word_ratio_compare",
    "task": "У Коли 12 наклеек, у Димы 3. Во сколько раз у Коли больше?",
    "expected": "4 раза",
    "source": "Math1 p.30-31"
  },
  {
    "id": "m1_multiply_groups",
    "category": "word_multiplication",
    "task": "В 4 коробках по 6 карандашей. Сколько всего карандашей?",
    "expected": "24",
    "source": "Math1 p.27-28"
  },
  {
    "id": "m1_share_equal",
    "category": "word_division_equal",
    "task": "24 конфеты разделили поровну между 6 детьми. Сколько получил каждый?",
    "expected": "4",
    "source": "Math1 p.29"
  },
  {
    "id": "m1_group_extra",
    "category": "word_extra_container",
    "task": "25 яблок разложили по 6 в коробки. Сколько коробок понадобится?",
    "expected": "5",
    "source": "Math1 p.34-36"
  },
  {
    "id": "m1_unknown_minuend",
    "category": "word_unknown_minuend",
    "task": "После того как съели 3 конфеты, осталось 5. Сколько было?",
    "expected": "8",
    "source": "Math1 p.19-20, 76"
  },
  {
    "id": "m1_unknown_addend_like",
    "category": "word_unknown_before_gain",
    "task": "После того как мама дала 3 яблока, стало 8. Сколько было?",
    "expected": "5",
    "source": "Math1 p.18-19"
  },
  {
    "id": "m1_find_added",
    "category": "word_find_added",
    "task": "Было 5 яблок, потом стало 8. Сколько добавили?",
    "expected": "3",
    "source": "Math1 p.18-19"
  },
  {
    "id": "m1_related_total",
    "category": "word_compound_related",
    "task": "У Маши 6 яблок, а у Пети на 2 больше. Сколько яблок у них вместе?",
    "expected": "14",
    "source": "Math1 p.23-24, 63-65"
  },
  {
    "id": "m1_sequential_change",
    "category": "word_sequential_change",
    "task": "В автобусе было 12 детей, на остановке вошли 3 и вышли 2. Сколько стало?",
    "expected": "13",
    "source": "Math1 p.24-25, 34-37"
  },
  {
    "id": "m1_groups_plus_extra",
    "category": "word_groups_plus_extra",
    "task": "В 3 коробках по 4 карандашей и ещё 5 карандаша отдельно. Сколько всего карандашей?",
    "expected": "17",
    "source": "Math1 p.39-43"
  },
  {
    "id": "m2_square_perimeter",
    "category": "geometry_square_perimeter",
    "task": "У квадрата сторона 6 см. Найди периметр.",
    "expected": "24 см",
    "source": "Math2 p.136-140"
  },
  {
    "id": "m2_square_area",
    "category": "geometry_square_area",
    "task": "У квадрата сторона 5 см. Найди площадь.",
    "expected": "25 см²",
    "source": "Math2 p.138-140"
  },
  {
    "id": "m2_inverse_square",
    "category": "geometry_square_side_from_perimeter",
    "task": "Периметр квадрата 20 см. Найди длину одной стороны квадрата.",
    "expected": "5 см",
    "source": "Math2 p.137-140"
  },
  {
    "id": "m2_inverse_rectangle_perimeter",
    "category": "geometry_rectangle_width_from_perimeter",
    "task": "Периметр прямоугольника 16 см. Найди ширину, если длина 5 см.",
    "expected": "3 см",
    "source": "Math2 p.137-140"
  },
  {
    "id": "m2_inverse_rectangle_area",
    "category": "geometry_rectangle_width_from_area",
    "task": "Площадь прямоугольника 24 см. Найди ширину, если длина 6 см.",
    "expected": "4 см",
    "source": "Math2 p.138-140"
  },
  {
    "id": "m2_fraction_add",
    "category": "fraction_arithmetic",
    "task": "1/2 + 1/4",
    "expected": "3/4",
    "source": "Math2 p.125-129"
  },
  {
    "id": "m2_fraction_sub",
    "category": "fraction_arithmetic",
    "task": "3/8 - 1/8",
    "expected": "1/4",
    "source": "Math2 p.125-129"
  },
  {
    "id": "m2_equation_addend",
    "category": "equation",
    "task": "x + 5 = 7",
    "expected": "2",
    "source": "Math2 p.79-83"
  },
  {
    "id": "m2_equation_factor",
    "category": "equation",
    "task": "x * 4 = 20",
    "expected": "5",
    "source": "Math2 p.79-83"
  },
  {
    "id": "m2_equation_divisor",
    "category": "equation",
    "task": "10 / x = 2",
    "expected": "5",
    "source": "Math2 p.79-83"
  },
  {
    "id": "m2_column_add",
    "category": "column_addition",
    "task": "36 + 18",
    "expected": "54",
    "source": "Math2 p.22-25"
  },
  {
    "id": "m2_column_sub",
    "category": "column_subtraction",
    "task": "53 - 25",
    "expected": "28",
    "source": "Math2 p.26-31"
  },
  {
    "id": "m2_column_mul",
    "category": "column_multiplication",
    "task": "327 * 3",
    "expected": "981",
    "source": "Math2 p.48-51"
  },
  {
    "id": "m2_column_div",
    "category": "column_division",
    "task": "125 : 8",
    "expected": "15, остаток 5",
    "source": "Math2 p.56-68"
  }
]